wagtail_guide/__init__.py
wagtail_guide/models.py
wagtail_guide/settings.py
wagtail_guide/views.py
wagtail_guide/wagtail_hooks.py
wagtail_guide/migrations/0001_initial.py
wagtail_guide/migrations/0002_alter_editorguide_sections_w30_usejsonfield.py
wagtail_guide/migrations/0003_alter_editorguide_sections.py
wagtail_guide/migrations/__init__.py
wagtail_guide/static/css/wagtailguide.css
wagtail_guide/templates/wagtail_guide/base.html
wagtail_guide/templates/wagtail_guide/streamfield/stream_block.html
wagtail_guide/templates/wagtail_guide/streamfield/blocks/embed_block.html
wagtail_guide/templates/wagtail_guide/streamfield/blocks/heading_block.html
wagtail_guide/templates/wagtail_guide/streamfield/blocks/image_block.html
wagtail_guide/templates/wagtail_guide/streamfield/blocks/pull_quote_block.html
wagtail_guide/templates/wagtail_guide/streamfield/blocks/quote_block.html
wagtail_guide/templates/wagtail_guide/streamfield/blocks/video_block.html
wagtail_guide/tests/__init__.py
wagtail_guide/tests/settings.py
wagtail_guide/tests/tests.py
wagtail_guide/tests/urls.py
wagtail_guide-2.2.0.dist-info/LICENSE
wagtail_guide-2.2.0.dist-info/METADATA
wagtail_guide-2.2.0.dist-info/WHEEL
wagtail_guide-2.2.0.dist-info/top_level.txt
wagtail_guide-2.2.0.dist-info/RECORD
