Metadata-Version: 2.1
Name: wagtail_guide
Version: 2.2.0
Summary: Adds functionality to add and edit a CMS guide page for editors.
Home-page: https://github.com/kevinhowbrook/wagtailguide
Author: Kevin Howbrook - Torchbox
Author-email: kevin.howbrook@torchbox.com
License: MIT
License-File: LICENSE
Requires-Dist: wagtail >=5.2
Requires-Dist: Django >=4.2
Provides-Extra: lint
Requires-Dist: black ==24.4.2 ; extra == 'lint'
Requires-Dist: isort ==5.13.2 ; extra == 'lint'
Requires-Dist: flake8 ==5.0.4 ; extra == 'lint'
Provides-Extra: testing
Requires-Dist: coverage ==6.4.1 ; extra == 'testing'
